find_dups/__init__.py
find_dups/main.py
find_dups/utils/__init__.py
find_dups/utils/file_dict_utils.py
find_dups/utils/fileutils.py
find_dups/utils/report.py
find_dups/utils/validation.py
find_dups-0.1.1.dist-info/WHEEL
find_dups-0.1.1.dist-info/entry_points.txt
find_dups-0.1.1.dist-info/METADATA
find_dups-0.1.1.dist-info/RECORD
