Metadata-Version: 2.4
Name: find-dups
Version: 0.1.1
Summary: Simple tool to find duplicate files in a directory tree.
Author: Sergio F. Gonzalez
Author-email: Sergio F. Gonzalez <sergio.f.gonzalez@gmail.com>
License-Expression: MIT
Requires-Python: >=3.12
Project-URL: Repository, https://github.com/sergiofgonzalez/find-dups
